{
  "updatedAt": "2026-06-02T11:55:02.102Z",
  "trendsFresh": true,
  "candidates": [
    {
      "id": "ivan_cepeda",
      "name": "Iván Cepeda",
      "party": "Pacto Histórico",
      "color": "#E63946",
      "trendsScore": 31,
      "youtubeScore": 100,
      "sentimentScore": 15,
      "sentimentPct": {
        "positive": 15.3,
        "negative": 62,
        "neutral": 22.7
      },
      "youtubeViews": 520937,
      "finalScore": 47,
      "momentum": {
        "value": -2.1,
        "direction": "flat"
      },
      "probability": 43.1
    },
    {
      "id": "abelardo_espriella",
      "name": "Abelardo de la Espriella",
      "party": "Defensores de la Patria",
      "color": "#1D3557",
      "trendsScore": 100,
      "youtubeScore": 52,
      "sentimentScore": 21,
      "sentimentPct": {
        "positive": 20.8,
        "negative": 49.6,
        "neutral": 29.6
      },
      "youtubeViews": 270845,
      "finalScore": 62,
      "momentum": {
        "value": 0,
        "direction": "flat"
      },
      "probability": 56.9
    }
  ],
  "articles": [
    {
      "title": "Así te lo contamos: De la Espriella y Cepeda pelearán por la presidencia de Colombia en segunda vuelta",
      "link": "https://www.bbc.co.uk/mundo/live/c62r12yy04xt?at_medium=RSS&at_campaign=rss",
      "source": "BBC Mundo",
      "pubDate": "2026-06-02T11:55:01.505Z",
      "candidateId": "ivan_cepeda",
      "candidateColor": "#E63946"
    },
    {
      "title": "MOE respondió al presidente Gustavo Petro tras anunciar que se pondrá al frente de campaña de Iván Cepeda: 'Excepto que tome la decisión de renunciar'",
      "link": "https://www.eltiempo.com/politica/elecciones-colombia-2026/moe-respondio-al-presidente-gustavo-petro-tras-anunciar-que-se-pondra-al-frente-de-campana-de-ivan-cepeda-la-decision-de-renunciar-3561367",
      "source": "El Tiempo",
      "pubDate": "2026-06-02T05:43:28-05:00",
      "candidateId": "ivan_cepeda",
      "candidateColor": "#E63946"
    },
    {
      "title": "‘Tuvimos una jornada electoral ejemplar’: registrador Hernán Penagos sobre elecciones presidenciales",
      "link": "https://www.eltiempo.com/politica/elecciones-colombia-2026/tuvimos-una-jornada-electoral-ejemplar-registrador-hernan-penagos-sobre-elecciones-presidenciales-3561324",
      "source": "El Tiempo",
      "pubDate": "2026-06-02T05:11:27-05:00",
      "candidateId": null,
      "candidateColor": "#64748b"
    },
    {
      "title": "Esta sería la nueva estrategia de Iván Cepeda para reunir tres millones de votos más para la segunda vuelta contra Abelardo de la Espriella",
      "link": "https://www.eltiempo.com/politica/elecciones-colombia-2026/esta-seria-la-nueva-estrategia-de-ivan-cepeda-para-reunir-tres-millones-de-votos-mas-para-la-segunda-vuelta-contra-abelardo-de-la-espriella-3561014",
      "source": "El Tiempo",
      "pubDate": "2026-06-01T22:01:00-05:00",
      "candidateId": "ivan_cepeda",
      "candidateColor": "#E63946"
    },
    {
      "title": "Colombia: Iván Cepeda listo para ir a debates; De la Espriella exige reconocimiento de resultados",
      "link": "https://www.france24.com/es/video/20260602-colombia-iv%C3%A1n-cepeda-listo-para-ir-a-debates-de-la-espriella-exige-reconocimiento-de-resultados",
      "source": "France 24",
      "pubDate": "Tue, 02 Jun 2026 02:22:29 GMT",
      "candidateId": "ivan_cepeda",
      "candidateColor": "#E63946"
    },
    {
      "title": "Registrador Nacional de Colombia defiende en France 24 la transparencia de las elecciones",
      "link": "https://www.france24.com/es/programas/la-entrevista/20260602-registrador-nacional-de-colombia-defiende-en-france-24-la-transparencia-de-las-elecciones",
      "source": "France 24",
      "pubDate": "Tue, 02 Jun 2026 00:24:48 GMT",
      "candidateId": "ivan_cepeda",
      "candidateColor": "#E63946"
    },
    {
      "title": "Directo a... Lima y el debate entre Keiko Fujimori y Roberto Sánchez",
      "link": "https://www.france24.com/es/video/20260602-directo-a-lima-y-el-debate-entre-keiko-fujimori-y-roberto-s%C3%A1nchez",
      "source": "France 24",
      "pubDate": "Tue, 02 Jun 2026 00:07:13 GMT",
      "candidateId": null,
      "candidateColor": "#64748b"
    },
    {
      "title": "Duerma informado con las claves de este 1 de junio de 2026",
      "link": "https://www.lasillavacia.com/en-vivo/duerma-informado-con-las-claves-de-este-1-de-junio-de-2026/",
      "source": "La Silla Vacía",
      "pubDate": "Tue, 02 Jun 2026 00:00:00 +0000",
      "candidateId": "ivan_cepeda",
      "candidateColor": "#E63946"
    },
    {
      "title": "Cepeda no tuvo ventaja en municipios con “riesgo de control criminal”",
      "link": "https://www.lasillavacia.com/en-vivo/cepeda-no-tuvo-ventaja-en-municipios-con-riesgo-de-control-criminal/",
      "source": "La Silla Vacía",
      "pubDate": "Mon, 01 Jun 2026 23:40:52 +0000",
      "candidateId": "abelardo_espriella",
      "candidateColor": "#1D3557"
    },
    {
      "title": "La primera vuelta en datos: así se dio la sorpresa de la derecha abelardista",
      "link": "https://www.lasillavacia.com/silla-nacional/la-primera-vuelta-en-datos-asi-se-dio-la-sorpresa-de-la-derecha-abelardista/",
      "source": "La Silla Vacía",
      "pubDate": "Mon, 01 Jun 2026 23:24:51 +0000",
      "candidateId": null,
      "candidateColor": "#64748b"
    },
    {
      "title": "El primer tiempo de la segunda vuelta",
      "link": "https://www.lasillavacia.com/opinion/el-primer-tiempo-de-la-segunda-vuelta/",
      "source": "La Silla Vacía",
      "pubDate": "Mon, 01 Jun 2026 23:03:17 +0000",
      "candidateId": null,
      "candidateColor": "#64748b"
    },
    {
      "title": "Campaña de Cepeda ya busca cafés con el centro para segunda vuelta",
      "link": "https://www.lasillavacia.com/en-vivo/campana-de-cepeda-ya-busca-cafes-con-el-centro-para-segunda-vuelta/",
      "source": "La Silla Vacía",
      "pubDate": "Mon, 01 Jun 2026 22:49:20 +0000",
      "candidateId": null,
      "candidateColor": "#64748b"
    }
  ]
}