{
  "updatedAt": "2026-05-17T14:43:49.300Z",
  "trendsFresh": true,
  "candidates": [
    {
      "id": "ivan_cepeda",
      "name": "Iván Cepeda",
      "party": "Pacto Histórico",
      "color": "#E63946",
      "trendsScore": 49,
      "youtubeScore": 97,
      "sentimentScore": 30,
      "sentimentPct": {
        "positive": 30.3,
        "negative": 38.3,
        "neutral": 31.3
      },
      "youtubeViews": 393379,
      "finalScore": 58,
      "momentum": {
        "value": 0,
        "direction": "flat"
      },
      "probability": 27.1
    },
    {
      "id": "abelardo_espriella",
      "name": "Abelardo de la Espriella",
      "party": "Defensores de la Patria",
      "color": "#1D3557",
      "trendsScore": 100,
      "youtubeScore": 84,
      "sentimentScore": 29,
      "sentimentPct": {
        "positive": 29.2,
        "negative": 41.6,
        "neutral": 29.2
      },
      "youtubeViews": 339490,
      "finalScore": 74,
      "momentum": {
        "value": 0,
        "direction": "flat"
      },
      "probability": 34.6
    },
    {
      "id": "paloma_valencia",
      "name": "Paloma Valencia",
      "party": "Centro Democrático",
      "color": "#457B9D",
      "trendsScore": 43,
      "youtubeScore": 70,
      "sentimentScore": 16,
      "sentimentPct": {
        "positive": 16.4,
        "negative": 55.9,
        "neutral": 27.7
      },
      "youtubeViews": 282459,
      "finalScore": 43,
      "momentum": {
        "value": 2.4,
        "direction": "flat"
      },
      "probability": 20.1
    },
    {
      "id": "sergio_fajardo",
      "name": "Sergio Fajardo",
      "party": "Coalición Centro Esperanza",
      "color": "#2A9D8F",
      "trendsScore": 7,
      "youtubeScore": 100,
      "sentimentScore": 19,
      "sentimentPct": {
        "positive": 18.8,
        "negative": 52,
        "neutral": 29.2
      },
      "youtubeViews": 404432,
      "finalScore": 39,
      "momentum": {
        "value": 0,
        "direction": "flat"
      },
      "probability": 18.2
    }
  ],
  "articles": [
    {
      "title": "“Ojalá Alex Saab no contrate un candidato de abogado”: Paloma",
      "link": "https://www.lasillavacia.com/en-vivo/ojala-alex-saab-no-contrate-un-candidato-de-abogado-paloma/",
      "source": "La Silla Vacía",
      "pubDate": "Sun, 17 May 2026 14:02:46 +0000",
      "candidateId": "abelardo_espriella",
      "candidateColor": "#1D3557"
    },
    {
      "title": "Qué sigue ahora que el JNE proclamó los resultados de la primera vuelta: prueba de color, debates y más",
      "link": "https://www.infobae.com/peru/2026/05/17/que-sigue-ahora-que-el-jne-proclamo-los-resultados-de-la-primera-vuelta-prueba-de-color-debates-y-mas/",
      "source": "Infobae",
      "pubDate": "Sun, 17 May 2026 13:39:47 +0000",
      "candidateId": null,
      "candidateColor": "#64748b"
    },
    {
      "title": "Abelardo de la Espriella se pronuncia tras asesinato de coordinador de su campaña en el Meta: 'Este crimen no es obra de desconocidos'",
      "link": "https://www.eltiempo.com/politica/elecciones-colombia-2026/abelardo-de-la-espriella-se-pronuncia-tras-asesinato-de-coordinador-de-su-campana-en-el-meta-este-crimen-no-es-obra-de-desconocidos-3556248",
      "source": "El Tiempo",
      "pubDate": "2026-05-16T11:23:54-05:00",
      "candidateId": "abelardo_espriella",
      "candidateColor": "#1D3557"
    },
    {
      "title": "Iván Cepeda califica de montaje audios atribuidos a jefe de disidencias de 'Calarcá': 'Hay una campaña sucia para enlodar mi prestigio'",
      "link": "https://www.eltiempo.com/politica/elecciones-colombia-2026/ivan-cepeda-califica-de-montaje-audios-atribuidos-a-jefe-de-disidencias-de-calarca-hay-una-campana-sucia-para-enlodar-mi-prestigio-3556093",
      "source": "El Tiempo",
      "pubDate": "2026-05-15T15:53:50-05:00",
      "candidateId": "ivan_cepeda",
      "candidateColor": "#E63946"
    }
  ]
}